eds4jinja2/__init__.py
eds4jinja2/adapters/__init__.py
eds4jinja2/adapters/base_data_source.py
eds4jinja2/adapters/file_ds.py
eds4jinja2/adapters/http_ds.py
eds4jinja2/adapters/latex_utils.py
eds4jinja2/adapters/local_sparql_ds.py
eds4jinja2/adapters/namespace_handler.py
eds4jinja2/adapters/prefix_cc_fetcher.py
eds4jinja2/adapters/remote_sparql_ds.py
eds4jinja2/adapters/substitution_template.py
eds4jinja2/adapters/tabular_utils.py
eds4jinja2/builders/__init__.py
eds4jinja2/builders/jinja_builder.py
eds4jinja2/builders/report_builder.py
eds4jinja2/builders/report_builder_actions.py
eds4jinja2/entrypoints/__init__.py
eds4jinja2/entrypoints/api/__init__.py
eds4jinja2/entrypoints/cli/__init__.py
eds4jinja2/entrypoints/cli/main.py
eds4jinja2-0.2.0.dist-info/LICENSE
eds4jinja2-0.2.0.dist-info/METADATA
eds4jinja2-0.2.0.dist-info/WHEEL
eds4jinja2-0.2.0.dist-info/entry_points.txt
eds4jinja2-0.2.0.dist-info/top_level.txt
eds4jinja2-0.2.0.dist-info/RECORD
